[
    {
        "index": 0,
        "Value": "605.0",
        "Forecast": "605.0",
        "Date": "1929-01-01",
        "Actual": ""
    },
    {
        "index": 1,
        "Value": "512.0",
        "Forecast": "512.0",
        "Date": "1930-01-01",
        "Actual": ""
    },
    {
        "index": 2,
        "Value": "435.0",
        "Forecast": "435.0",
        "Date": "1931-01-01",
        "Actual": ""
    },
    {
        "index": 3,
        "Value": "308.0",
        "Forecast": "308.0",
        "Date": "1932-01-01",
        "Actual": ""
    },
    {
        "index": 4,
        "Value": "294.0",
        "Forecast": "294.0",
        "Date": "1933-01-01",
        "Actual": ""
    },
    {
        "index": 5,
        "Value": "357.0",
        "Forecast": "357.0",
        "Date": "1934-01-01",
        "Actual": ""
    },
    {
        "index": 6,
        "Value": "419.0",
        "Forecast": "419.0",
        "Date": "1935-01-01",
        "Actual": ""
    },
    {
        "index": 7,
        "Value": "481.0",
        "Forecast": "481.0",
        "Date": "1936-01-01",
        "Actual": ""
    },
    {
        "index": 8,
        "Value": "546.0",
        "Forecast": "546.0",
        "Date": "1937-01-01",
        "Actual": ""
    },
    {
        "index": 9,
        "Value": "472.0",
        "Forecast": "472.0",
        "Date": "1938-01-01",
        "Actual": ""
    },
    {
        "index": 10,
        "Value": "518.0",
        "Forecast": "518.0",
        "Date": "1939-01-01",
        "Actual": ""
    },
    {
        "index": 11,
        "Value": "552.0",
        "Forecast": "552.0",
        "Date": "1940-01-01",
        "Actual": ""
    },
    {
        "index": 12,
        "Value": "726.0",
        "Forecast": "726.0",
        "Date": "1941-01-01",
        "Actual": ""
    },
    {
        "index": 13,
        "Value": "919.0",
        "Forecast": "919.0",
        "Date": "1942-01-01",
        "Actual": ""
    },
    {
        "index": 14,
        "Value": "1150.0",
        "Forecast": "1150.0",
        "Date": "1943-01-01",
        "Actual": ""
    },
    {
        "index": 15,
        "Value": "1209.0",
        "Forecast": "1209.0",
        "Date": "1944-01-01",
        "Actual": ""
    },
    {
        "index": 16,
        "Value": "1265.0",
        "Forecast": "1265.0",
        "Date": "1945-01-01",
        "Actual": ""
    },
    {
        "index": 17,
        "Value": "1211.0",
        "Forecast": "1211.0",
        "Date": "1946-01-01",
        "Actual": ""
    },
    {
        "index": 18,
        "Value": "1316.0",
        "Forecast": "1316.0",
        "Date": "1947-01-01",
        "Actual": ""
    },
    {
        "index": 19,
        "Value": "1448.0",
        "Forecast": "1448.0",
        "Date": "1948-01-01",
        "Actual": ""
    },
    {
        "index": 20,
        "Value": "1357.0",
        "Forecast": "1357.0",
        "Date": "1949-01-01",
        "Actual": ""
    },
    {
        "index": 21,
        "Value": "1525.0",
        "Forecast": "1525.0",
        "Date": "1950-01-01",
        "Actual": ""
    },
    {
        "index": 22,
        "Value": "1719.0",
        "Forecast": "1719.0",
        "Date": "1951-01-01",
        "Actual": ""
    },
    {
        "index": 23,
        "Value": "1786.0",
        "Forecast": "1786.0",
        "Date": "1952-01-01",
        "Actual": ""
    },
    {
        "index": 24,
        "Value": "1952.0",
        "Forecast": "1952.0",
        "Date": "1953-01-01",
        "Actual": ""
    },
    {
        "index": 25,
        "Value": "1810.0",
        "Forecast": "1810.0",
        "Date": "1954-01-01",
        "Actual": ""
    },
    {
        "index": 26,
        "Value": "1908.0",
        "Forecast": "1908.0",
        "Date": "1955-01-01",
        "Actual": ""
    },
    {
        "index": 27,
        "Value": "2011.0",
        "Forecast": "2011.0",
        "Date": "1956-01-01",
        "Actual": ""
    },
    {
        "index": 28,
        "Value": "2046.0",
        "Forecast": "2046.0",
        "Date": "1957-01-01",
        "Actual": ""
    },
    {
        "index": 29,
        "Value": "2023.0",
        "Forecast": "2023.0",
        "Date": "1958-01-01",
        "Actual": ""
    },
    {
        "index": 30,
        "Value": "2141.0",
        "Forecast": "2141.0",
        "Date": "1959-01-01",
        "Actual": ""
    },
    {
        "index": 31,
        "Value": "2223.0",
        "Forecast": "2223.0",
        "Date": "1960-01-01",
        "Actual": ""
    },
    {
        "index": 32,
        "Value": "2264.0",
        "Forecast": "2264.0",
        "Date": "1961-01-01",
        "Actual": ""
    },
    {
        "index": 33,
        "Value": "2421.0",
        "Forecast": "2421.0",
        "Date": "1962-01-01",
        "Actual": ""
    },
    {
        "index": 34,
        "Value": "2509.0",
        "Forecast": "2509.0",
        "Date": "1963-01-01",
        "Actual": ""
    },
    {
        "index": 35,
        "Value": "2639.0",
        "Forecast": "2639.0",
        "Date": "1964-01-01",
        "Actual": ""
    },
    {
        "index": 36,
        "Value": "2877.0",
        "Forecast": "2877.0",
        "Date": "1965-01-01",
        "Actual": ""
    },
    {
        "index": 37,
        "Value": "3058.0",
        "Forecast": "3058.0",
        "Date": "1966-01-01",
        "Actual": ""
    },
    {
        "index": 38,
        "Value": "3170.0",
        "Forecast": "3170.0",
        "Date": "1967-01-01",
        "Actual": ""
    },
    {
        "index": 39,
        "Value": "3419.0",
        "Forecast": "3419.0",
        "Date": "1968-01-01",
        "Actual": ""
    },
    {
        "index": 40,
        "Value": "3741.0",
        "Forecast": "3741.0",
        "Date": "1969-01-01",
        "Actual": ""
    },
    {
        "index": 41,
        "Value": "3849.0",
        "Forecast": "3849.0",
        "Date": "1970-01-01",
        "Actual": ""
    },
    {
        "index": 42,
        "Value": "4151.0",
        "Forecast": "4151.0",
        "Date": "1971-01-01",
        "Actual": ""
    },
    {
        "index": 43,
        "Value": "4503.0",
        "Forecast": "4503.0",
        "Date": "1972-01-01",
        "Actual": ""
    },
    {
        "index": 44,
        "Value": "5136.0",
        "Forecast": "5136.0",
        "Date": "1973-01-01",
        "Actual": ""
    },
    {
        "index": 45,
        "Value": "5472.0",
        "Forecast": "5472.0",
        "Date": "1974-01-01",
        "Actual": ""
    },
    {
        "index": 46,
        "Value": "5907.0",
        "Forecast": "5907.0",
        "Date": "1975-01-01",
        "Actual": ""
    },
    {
        "index": 47,
        "Value": "6540.0",
        "Forecast": "6540.0",
        "Date": "1976-01-01",
        "Actual": ""
    },
    {
        "index": 48,
        "Value": "7197.0",
        "Forecast": "7197.0",
        "Date": "1977-01-01",
        "Actual": ""
    },
    {
        "index": 49,
        "Value": "7968.0",
        "Forecast": "7968.0",
        "Date": "1978-01-01",
        "Actual": ""
    },
    {
        "index": 50,
        "Value": "8732.0",
        "Forecast": "8732.0",
        "Date": "1979-01-01",
        "Actual": ""
    },
    {
        "index": 51,
        "Value": "9368.0",
        "Forecast": "9368.0",
        "Date": "1980-01-01",
        "Actual": ""
    },
    {
        "index": 52,
        "Value": "10288.0",
        "Forecast": "10288.0",
        "Date": "1981-01-01",
        "Actual": ""
    },
    {
        "index": 53,
        "Value": "10682.0",
        "Forecast": "10682.0",
        "Date": "1982-01-01",
        "Actual": ""
    },
    {
        "index": 54,
        "Value": "11246.0",
        "Forecast": "11246.0",
        "Date": "1983-01-01",
        "Actual": ""
    },
    {
        "index": 55,
        "Value": "12448.0",
        "Forecast": "12448.0",
        "Date": "1984-01-01",
        "Actual": ""
    },
    {
        "index": 56,
        "Value": "13149.0",
        "Forecast": "13149.0",
        "Date": "1985-01-01",
        "Actual": ""
    },
    {
        "index": 57,
        "Value": "13862.0",
        "Forecast": "13862.0",
        "Date": "1986-01-01",
        "Actual": ""
    },
    {
        "index": 58,
        "Value": "14616.0",
        "Forecast": "14616.0",
        "Date": "1987-01-01",
        "Actual": ""
    },
    {
        "index": 59,
        "Value": "15634.0",
        "Forecast": "15634.0",
        "Date": "1988-01-01",
        "Actual": ""
    },
    {
        "index": 60,
        "Value": "16924.0",
        "Forecast": "16924.0",
        "Date": "1989-01-01",
        "Actual": ""
    },
    {
        "index": 61,
        "Value": "17763.0",
        "Forecast": "17763.0",
        "Date": "1990-01-01",
        "Actual": ""
    },
    {
        "index": 62,
        "Value": "18134.0",
        "Forecast": "18134.0",
        "Date": "1991-01-01",
        "Actual": ""
    },
    {
        "index": 63,
        "Value": "19396.0",
        "Forecast": "19396.0",
        "Date": "1992-01-01",
        "Actual": ""
    },
    {
        "index": 64,
        "Value": "20212.0",
        "Forecast": "20212.0",
        "Date": "1993-01-01",
        "Actual": ""
    },
    {
        "index": 65,
        "Value": "21271.0",
        "Forecast": "21271.0",
        "Date": "1994-01-01",
        "Actual": ""
    },
    {
        "index": 66,
        "Value": "22014.0",
        "Forecast": "22014.0",
        "Date": "1995-01-01",
        "Actual": ""
    },
    {
        "index": 67,
        "Value": "23043.0",
        "Forecast": "23043.0",
        "Date": "1996-01-01",
        "Actual": ""
    },
    {
        "index": 68,
        "Value": "24066.0",
        "Forecast": "24066.0",
        "Date": "1997-01-01",
        "Actual": ""
    },
    {
        "index": 69,
        "Value": "25758.0",
        "Forecast": "25758.0",
        "Date": "1998-01-01",
        "Actual": ""
    },
    {
        "index": 70,
        "Value": "26545.0",
        "Forecast": "26545.0",
        "Date": "1999-01-01",
        "Actual": ""
    },
    {
        "index": 71,
        "Value": "28075.0",
        "Forecast": "28075.0",
        "Date": "2000-01-01",
        "Actual": ""
    },
    {
        "index": 72,
        "Value": "28596.0",
        "Forecast": "28596.0",
        "Date": "2001-01-01",
        "Actual": ""
    },
    {
        "index": 73,
        "Value": "28902.0",
        "Forecast": "28902.0",
        "Date": "2002-01-01",
        "Actual": ""
    },
    {
        "index": 74,
        "Value": "29445.0",
        "Forecast": "29445.0",
        "Date": "2003-01-01",
        "Actual": ""
    },
    {
        "index": 75,
        "Value": "30657.0",
        "Forecast": "30657.0",
        "Date": "2004-01-01",
        "Actual": ""
    },
    {
        "index": 76,
        "Value": "31376.0",
        "Forecast": "31376.0",
        "Date": "2005-01-01",
        "Actual": ""
    },
    {
        "index": 77,
        "Value": "32905.0",
        "Forecast": "32905.0",
        "Date": "2006-01-01",
        "Actual": ""
    },
    {
        "index": 78,
        "Value": "33845.0",
        "Forecast": "33845.0",
        "Date": "2007-01-01",
        "Actual": ""
    },
    {
        "index": 79,
        "Value": "35270.0",
        "Forecast": "35270.0",
        "Date": "2008-01-01",
        "Actual": ""
    },
    {
        "index": 80,
        "Value": "34200.0",
        "Forecast": "34200.0",
        "Date": "2009-01-01",
        "Actual": ""
    },
    {
        "index": 81,
        "Value": "35590.0",
        "Forecast": "35590.0",
        "Date": "2010-01-01",
        "Actual": ""
    },
    {
        "index": 82,
        "Value": "37682.0",
        "Forecast": "37682.0",
        "Date": "2011-01-01",
        "Actual": ""
    },
    {
        "index": 83,
        "Value": "39150.0",
        "Forecast": "39150.0",
        "Date": "2012-01-01",
        "Actual": ""
    },
    {
        "index": 84,
        "Value": "39436.0",
        "Forecast": "39436.0",
        "Date": "2013-01-01",
        "Actual": ""
    },
    {
        "index": 85,
        "Value": "40721.0",
        "Forecast": "40721.0",
        "Date": "2014-01-01",
        "Actual": ""
    },
    {
        "index": 86,
        "Value": "42149.0",
        "Forecast": "42149.0",
        "Date": "2015-01-01",
        "Actual": ""
    },
    {
        "index": 87,
        "Value": "43145.0",
        "Forecast": "43145.0",
        "Date": "2016-01-01",
        "Actual": ""
    },
    {
        "index": 88,
        "Value": "44570.0",
        "Forecast": "44570.0",
        "Date": "2017-01-01",
        "Actual": ""
    },
    {
        "index": 89,
        "Value": "46556.0",
        "Forecast": "46556.0",
        "Date": "2018-01-01",
        "Actual": ""
    },
    {
        "index": 90,
        "Value": "48270.0",
        "Forecast": "48270.0",
        "Date": "2019-01-01",
        "Actual": ""
    },
    {
        "index": 91,
        "Value": "51719.0",
        "Forecast": "51719.0",
        "Date": "2020-01-01",
        "Actual": ""
    },
    {
        "index": 92,
        "Value": "56934.0",
        "Forecast": "56934.0",
        "Date": "2021-01-01",
        "Actual": ""
    },
    {
        "index": 93,
        "Value": "58323.0",
        "Forecast": "58323.0",
        "Date": "2022-01-01",
        "Actual": ""
    },
    {
        "index": 94,
        "Value": "51814.6796875",
        "Forecast": "51814.6796875",
        "Date": "2023-01-01",
        "Actual": ""
    },
    {
        "index": 95,
        "Value": "46235.43359375",
        "Forecast": "46235.43359375",
        "Date": "2024-01-01",
        "Actual": ""
    },
    {
        "index": 96,
        "Value": "48920.5859375",
        "Forecast": "48920.5859375",
        "Date": "2025-01-01",
        "Actual": ""
    },
    {
        "index": 97,
        "Value": "48660.01171875",
        "Forecast": "48660.01171875",
        "Date": "2026-01-01",
        "Actual": ""
    },
    {
        "index": 98,
        "Value": "52220.90625",
        "Forecast": "52220.90625",
        "Date": "2027-01-01",
        "Actual": ""
    },
    {
        "index": 99,
        "Value": "55076.1953125",
        "Forecast": "55076.1953125",
        "Date": "2028-01-01",
        "Actual": ""
    },
    {
        "index": 100,
        "Value": "64681.34375",
        "Forecast": "64681.34375",
        "Date": "2029-01-01",
        "Actual": ""
    },
    {
        "index": 101,
        "Value": "52360.3125",
        "Forecast": "52360.3125",
        "Date": "2030-01-01",
        "Actual": ""
    },
    {
        "index": 102,
        "Value": "53895.984375",
        "Forecast": "53895.984375",
        "Date": "2031-01-01",
        "Actual": ""
    },
    {
        "index": 103,
        "Value": "64533.4609375",
        "Forecast": "64533.4609375",
        "Date": "2032-01-01",
        "Actual": ""
    },
    {
        "index": 104,
        "Value": "59550.37109375",
        "Forecast": "59550.37109375",
        "Date": "2033-01-01",
        "Actual": ""
    },
    {
        "index": 105,
        "Value": "59990.45703125",
        "Forecast": "59990.45703125",
        "Date": "2034-01-01",
        "Actual": ""
    },
    {
        "index": 106,
        "Value": "66090.1328125",
        "Forecast": "66090.1328125",
        "Date": "2035-01-01",
        "Actual": ""
    },
    {
        "index": 107,
        "Value": "68425.25",
        "Forecast": "68425.25",
        "Date": "2036-01-01",
        "Actual": ""
    },
    {
        "index": 108,
        "Value": "65973.6484375",
        "Forecast": "65973.6484375",
        "Date": "2037-01-01",
        "Actual": ""
    },
    {
        "index": 109,
        "Value": "62529.06640625",
        "Forecast": "62529.06640625",
        "Date": "2038-01-01",
        "Actual": ""
    },
    {
        "index": 110,
        "Value": "71471.6953125",
        "Forecast": "71471.6953125",
        "Date": "2039-01-01",
        "Actual": ""
    },
    {
        "index": 111,
        "Value": "72316.3125",
        "Forecast": "72316.3125",
        "Date": "2040-01-01",
        "Actual": ""
    },
    {
        "index": 112,
        "Value": "71005.28125",
        "Forecast": "71005.28125",
        "Date": "2041-01-01",
        "Actual": ""
    },
    {
        "index": 113,
        "Value": "77324.8125",
        "Forecast": "77324.8125",
        "Date": "2042-01-01",
        "Actual": ""
    },
    {
        "index": 114,
        "Value": "67573.5625",
        "Forecast": "67573.5625",
        "Date": "2043-01-01",
        "Actual": ""
    },
    {
        "index": 115,
        "Value": "67755.3125",
        "Forecast": "67755.3125",
        "Date": "2044-01-01",
        "Actual": ""
    },
    {
        "index": 116,
        "Value": "75826.640625",
        "Forecast": "75826.640625",
        "Date": "2045-01-01",
        "Actual": ""
    },
    {
        "index": 117,
        "Value": "85540.796875",
        "Forecast": "85540.796875",
        "Date": "2046-01-01",
        "Actual": ""
    },
    {
        "index": 118,
        "Value": "75566.25",
        "Forecast": "75566.25",
        "Date": "2047-01-01",
        "Actual": ""
    },
    {
        "index": 119,
        "Value": "78688.625",
        "Forecast": "78688.625",
        "Date": "2048-01-01",
        "Actual": ""
    },
    {
        "index": 120,
        "Value": "78730.1484375",
        "Forecast": "78730.1484375",
        "Date": "2049-01-01",
        "Actual": ""
    },
    {
        "index": 121,
        "Value": "90598.953125",
        "Forecast": "90598.953125",
        "Date": "2050-01-01",
        "Actual": ""
    },
    {
        "index": 122,
        "Value": "88317.375",
        "Forecast": "88317.375",
        "Date": "2051-01-01",
        "Actual": ""
    },
    {
        "index": 123,
        "Value": "97567.4453125",
        "Forecast": "97567.4453125",
        "Date": "2052-01-01",
        "Actual": ""
    }
]